[{"distinct_id": "183e37152b1435-0103a4ac31f79f8-2a6d4e34-4a640-183e37152b29dd", "event": "Visit Detail Shrimp Price", "timestamp": "2022-11-03T13:50:52.389Z", "uuid": "01843dc2-51f6-0000-4d37-70313a17a0fd", "elements": [], "$geoip_city_name": "Banda Aceh", "$geoip_country_name": "Indonesia", "$geoip_country_code": "ID", "$geoip_continent_name": "Asia", "$geoip_continent_code": "AS", "$geoip_latitude": 5.5418, "$geoip_longitude": 95.3413, "$geoip_time_zone": "Asia/Jakarta", "$geoip_subdivision_1_code": "AC", "$geoip_subdivision_1_name": "Aceh"}]