[{"distinct_id": "1840dfcacc81b3-020616279382ee-615a2225-448e0-1840dfcacc9153", "event": "$pageleave", "timestamp": "2022-11-03T14:02:52.079Z", "uuid": "01843dcd-3f35-0000-fbb9-6d2f0097f206", "elements": [], "$geoip_city_name": "Tangerang", "$geoip_country_name": "Indonesia", "$geoip_country_code": "ID", "$geoip_continent_name": "Asia", "$geoip_continent_code": "AS", "$geoip_latitude": -6.177, "$geoip_longitude": 106.6284, "$geoip_time_zone": "Asia/Jakarta", "$geoip_subdivision_1_code": "BT", "$geoip_subdivision_1_name": "Banten"}, {"distinct_id": "4318", "event": "Fasting: Created", "timestamp": "2022-11-03T14:02:59.000Z", "uuid": "01843dcd-5f85-0000-7cdc-16df1611b308", "elements": [], "$geoip_city_name": "Singapore", "$geoip_country_name": "Singapore", "$geoip_country_code": "SG", "$geoip_continent_name": "Asia", "$geoip_continent_code": "AS", "$geoip_latitude": 1.3036, "$geoip_longitude": 103.8554, "$geoip_time_zone": "Asia/Singapore"}]