[{"distinct_id": "15617", "event": "$pageleave", "timestamp": "2022-11-19T08:07:34.273Z", "uuid": "01848eed-b68b-0000-aa67-22cf0e7f07c3", "elements": [], "$geoip_city_name": "Bali", "$geoip_country_name": "Indonesia", "$geoip_country_code": "ID", "$geoip_continent_name": "Asia", "$geoip_continent_code": "AS", "$geoip_latitude": -8.4994, "$geoip_longitude": 115.004, "$geoip_time_zone": "Asia/Makassar", "$geoip_subdivision_1_code": "BA", "$geoip_subdivision_1_name": "Bali"}, {"distinct_id": "22573", "event": "$pageleave", "timestamp": "2022-11-19T08:07:34.832Z", "uuid": "01848eed-b8be-0000-a258-62ec606be947", "elements": [], "$geoip_city_name": "Surabaya", "$geoip_country_name": "Indonesia", "$geoip_country_code": "ID", "$geoip_continent_name": "Asia", "$geoip_continent_code": "AS", "$geoip_latitude": -7.2484, "$geoip_longitude": 112.7419, "$geoip_time_zone": "Asia/Jakarta", "$geoip_subdivision_1_code": "JI", "$geoip_subdivision_1_name": "East Java"}, {"distinct_id": "15617", "event": "$pageview", "timestamp": "2022-11-19T08:07:35.207Z", "uuid": "01848eed-ba2c-0000-8644-670f81cedf65", "elements": [], "$geoip_city_name": "Bali", "$geoip_country_name": "Indonesia", "$geoip_country_code": "ID", "$geoip_continent_name": "Asia", "$geoip_continent_code": "AS", "$geoip_latitude": -8.4994, "$geoip_longitude": 115.004, "$geoip_time_zone": "Asia/Makassar", "$geoip_subdivision_1_code": "BA", "$geoip_subdivision_1_name": "Bali"}, {"distinct_id": "22573", "event": "$pageview", "timestamp": "2022-11-19T08:07:35.732Z", "uuid": "01848eed-bc39-0000-2c81-c1d76c91621b", "elements": [], "$geoip_city_name": "Surabaya", "$geoip_country_name": "Indonesia", "$geoip_country_code": "ID", "$geoip_continent_name": "Asia", "$geoip_continent_code": "AS", "$geoip_latitude": -7.2484, "$geoip_longitude": 112.7419, "$geoip_time_zone": "Asia/Jakarta", "$geoip_subdivision_1_code": "JI", "$geoip_subdivision_1_name": "East Java"}, {"distinct_id": "21942", "event": "Web Session", "timestamp": "2022-11-19T08:07:36.066Z", "uuid": "01848eed-c430-0000-1dc7-72ad9ec812f6", "elements": [], "$geoip_city_name": "Sukabumi", "$geoip_country_name": "Indonesia", "$geoip_country_code": "ID", "$geoip_continent_name": "Asia", "$geoip_continent_code": "AS", "$geoip_latitude": -6.9214, "$geoip_longitude": 106.9259, "$geoip_time_zone": "Asia/Jakarta", "$geoip_subdivision_1_code": "JB", "$geoip_subdivision_1_name": "West Java"}, {"distinct_id": "862549047820231", "event": "MultiMeasurement: Created", "timestamp": "2022-11-19T08:07:39.000Z", "uuid": "01848eed-cd59-0000-ba19-abf609c79b6e", "elements": [], "$geoip_city_name": "Singapore", "$geoip_country_name": "Singapore", "$geoip_country_code": "SG", "$geoip_continent_name": "Asia", "$geoip_continent_code": "AS", "$geoip_latitude": 1.3036, "$geoip_longitude": 103.8554, "$geoip_time_zone": "Asia/Singapore"}, {"distinct_id": "21942", "event": "$identify", "timestamp": "2022-11-19T08:07:44.288Z", "uuid": "01848eed-dda4-0000-d56f-db5a6e1428a5", "elements": [], "$geoip_city_name": "Sukabumi", "$geoip_country_name": "Indonesia", "$geoip_country_code": "ID", "$geoip_continent_name": "Asia", "$geoip_continent_code": "AS", "$geoip_latitude": -6.9214, "$geoip_longitude": 106.9259, "$geoip_time_zone": "Asia/Jakarta", "$geoip_subdivision_1_code": "JB", "$geoip_subdivision_1_name": "West Java"}]