[{"distinct_id": "21842", "event": "Mobile app: home - notifications - cultivation", "timestamp": "2022-10-26T00:15:18.994Z", "uuid": "018411a4-d9e8-0001-e421-959766f29557", "elements": [], "$geoip_city_name": "East Java", "$geoip_country_name": "Indonesia", "$geoip_country_code": "ID", "$geoip_continent_name": "Asia", "$geoip_continent_code": "AS", "$geoip_latitude": -7.7394, "$geoip_longitude": 112.5099, "$geoip_time_zone": "Asia/Jakarta", "$geoip_subdivision_1_code": "JI", "$geoip_subdivision_1_name": "East Java"}, {"distinct_id": "21859", "event": "input-modal-feed filling form", "timestamp": "2022-10-26T00:15:28.691Z", "uuid": "018411a4-e043-0002-5b0f-67cfecb07636", "elements": [], "$geoip_city_name": "Semarang", "$geoip_country_name": "Indonesia", "$geoip_country_code": "ID", "$geoip_continent_name": "Asia", "$geoip_continent_code": "AS", "$geoip_latitude": -6.9932, "$geoip_longitude": 110.4215, "$geoip_time_zone": "Asia/Jakarta", "$geoip_subdivision_1_code": "JT", "$geoip_subdivision_1_name": "Central Java"}]