[{"distinct_id": "21929", "event": "Multi Measurement: Created", "timestamp": "2022-10-26T01:44:41.000Z", "uuid": "018411f6-8fa2-0000-f015-42938404e728", "elements": [], "$geoip_city_name": "Singapore", "$geoip_country_name": "Singapore", "$geoip_country_code": "SG", "$geoip_continent_name": "Asia", "$geoip_continent_code": "AS", "$geoip_latitude": 1.3036, "$geoip_longitude": 103.8554, "$geoip_time_zone": "Asia/Singapore"}, {"distinct_id": "21398", "event": "Mobile app: feed - edit", "timestamp": "2022-10-26T01:44:36.287Z", "uuid": "018411f6-90d5-0002-7c03-5efcc8bf33e6", "elements": [], "$geoip_city_name": "Jakarta", "$geoip_country_name": "Indonesia", "$geoip_country_code": "ID", "$geoip_continent_name": "Asia", "$geoip_continent_code": "AS", "$geoip_latitude": -6.2114, "$geoip_longitude": 106.8446, "$geoip_time_zone": "Asia/Jakarta", "$geoip_subdivision_1_code": "JK", "$geoip_subdivision_1_name": "Jakarta"}]