[{"distinct_id": "15707", "event": "Sampling: Created", "timestamp": "2022-10-20T09:37:48.000Z", "uuid": "0183f4c1-8edc-0000-9b47-2165441c13a5", "elements": [], "$geoip_city_name": "Singapore", "$geoip_country_name": "Singapore", "$geoip_country_code": "SG", "$geoip_continent_name": "Asia", "$geoip_continent_code": "AS", "$geoip_latitude": 1.3036, "$geoip_longitude": 103.8554, "$geoip_time_zone": "Asia/Singapore"}, {"distinct_id": "183f4c1e35a3f-08bb835fe0f19b-4669495e-43da0-183f4c1e35b74", "event": "$pageview", "timestamp": "2022-10-20T09:38:12.673Z", "uuid": "0183f4c1-ea4a-0000-33fa-9262da5a37d3", "elements": [], "$geoip_city_name": "Bandar Lampung", "$geoip_country_name": "Indonesia", "$geoip_country_code": "ID", "$geoip_continent_name": "Asia", "$geoip_continent_code": "AS", "$geoip_latitude": -5.4291, "$geoip_longitude": 105.2615, "$geoip_time_zone": "Asia/Jakarta", "$geoip_subdivision_1_code": "LA", "$geoip_subdivision_1_name": "Lampung"}, {"distinct_id": "183f374f8678f-06512021822fa-536c4937-100200-183f374f869c90", "event": "$pageview", "timestamp": "2022-10-20T09:38:34.179Z", "uuid": "0183f4c2-3e4e-0000-fccf-b94251f96d7f", "elements": [], "$geoip_country_name": "Indonesia", "$geoip_country_code": "ID", "$geoip_continent_name": "Asia", "$geoip_continent_code": "AS", "$geoip_latitude": -6.1728, "$geoip_longitude": 106.8272, "$geoip_time_zone": "Asia/Jakarta"}]