[{"distinct_id": "183cd2a5a8b3d1-0224509142a084-26021f51-100200-183cd2a5a8c200", "event": "Visit Detail Newsfeed", "timestamp": "2022-10-12T17:07:28.946Z", "uuid": "0183cd2a-6bad-0000-4f73-02246fb5910b", "elements": [], "$geoip_city_name": "Semarang", "$geoip_country_name": "Indonesia", "$geoip_country_code": "ID", "$geoip_continent_name": "Asia", "$geoip_continent_code": "AS", "$geoip_latitude": -6.9932, "$geoip_longitude": 110.4215, "$geoip_time_zone": "Asia/Jakarta", "$geoip_subdivision_1_code": "JT", "$geoip_subdivision_1_name": "Central Java"}]