[{"distinct_id": "12389", "event": "Mobile app: pond - add feed", "timestamp": "2022-11-17T23:18:20.577Z", "uuid": "018487e2-e428-0001-3d92-78db9e306ac0", "elements": [], "$geoip_city_name": "Sukabumi", "$geoip_country_name": "Indonesia", "$geoip_country_code": "ID", "$geoip_continent_name": "Asia", "$geoip_continent_code": "AS", "$geoip_latitude": -6.9214, "$geoip_longitude": 106.9259, "$geoip_time_zone": "Asia/Jakarta", "$geoip_subdivision_1_code": "JB", "$geoip_subdivision_1_name": "West Java"}]