[{"distinct_id": "22062", "event": "Web Session", "timestamp": "2022-11-15T01:58:24.137Z", "uuid": "01847902-52eb-0000-68ab-9bee44236220", "elements": [], "$geoip_city_name": "Jakarta", "$geoip_country_name": "Indonesia", "$geoip_country_code": "ID", "$geoip_continent_name": "Asia", "$geoip_continent_code": "AS", "$geoip_latitude": -6.2114, "$geoip_longitude": 106.8446, "$geoip_time_zone": "Asia/Jakarta", "$geoip_subdivision_1_code": "JK", "$geoip_subdivision_1_name": "Jakarta"}, {"distinct_id": "21367", "event": "input-modal-measurement add pond", "timestamp": "2022-11-15T01:58:29.445Z", "uuid": "01847902-62a4-0001-143f-8f7b9099161f", "elements": [], "$geoip_city_name": "Nampula", "$geoip_country_name": "Mozambique", "$geoip_country_code": "MZ", "$geoip_continent_name": "Africa", "$geoip_continent_code": "AF", "$geoip_latitude": -15.1185, "$geoip_longitude": 39.2695, "$geoip_time_zone": "Africa/Maputo", "$geoip_subdivision_1_code": "N", "$geoip_subdivision_1_name": "Nampula"}, {"distinct_id": "22062", "event": "$identify", "timestamp": "2022-11-15T01:58:31.544Z", "uuid": "01847902-6782-0000-5ec5-a310b871b34c", "elements": [], "$geoip_city_name": "Jakarta", "$geoip_country_name": "Indonesia", "$geoip_country_code": "ID", "$geoip_continent_name": "Asia", "$geoip_continent_code": "AS", "$geoip_latitude": -6.2114, "$geoip_longitude": 106.8446, "$geoip_time_zone": "Asia/Jakarta", "$geoip_subdivision_1_code": "JK", "$geoip_subdivision_1_name": "Jakarta"}]