[{"distinct_id": "21408", "event": "Measurement: Updated", "timestamp": "2022-11-09T05:20:49.000Z", "uuid": "01845ad5-78cf-0000-7897-7e05eaf07961", "elements": [], "$geoip_city_name": "Singapore", "$geoip_country_name": "Singapore", "$geoip_country_code": "SG", "$geoip_continent_name": "Asia", "$geoip_continent_code": "AS", "$geoip_latitude": 1.3036, "$geoip_longitude": 103.8554, "$geoip_time_zone": "Asia/Singapore"}, {"distinct_id": "19770", "event": "Web Session", "timestamp": "2022-11-09T05:20:50.552Z", "uuid": "01845ad5-7f10-0000-72b7-936c6e26b942", "elements": [], "$geoip_city_name": "Nampula", "$geoip_country_name": "Mozambique", "$geoip_country_code": "MZ", "$geoip_continent_name": "Africa", "$geoip_continent_code": "AF", "$geoip_latitude": -15.1185, "$geoip_longitude": 39.2695, "$geoip_time_zone": "Africa/Maputo", "$geoip_subdivision_1_code": "N", "$geoip_subdivision_1_name": "Nampula"}, {"distinct_id": "21408", "event": "Measurement: Updated", "timestamp": "2022-11-09T05:20:53.000Z", "uuid": "01845ad5-8727-0000-84f0-2c93067de751", "elements": [], "$geoip_city_name": "Singapore", "$geoip_country_name": "Singapore", "$geoip_country_code": "SG", "$geoip_continent_name": "Asia", "$geoip_continent_code": "AS", "$geoip_latitude": 1.3036, "$geoip_longitude": 103.8554, "$geoip_time_zone": "Asia/Singapore"}]