[{"distinct_id": "18282d2c8ed8e-0ce516655b425d-46686469-46500-18282d2c8ee106", "event": "$pageview", "timestamp": "2022-10-15T16:59:11.978Z", "uuid": "0183dc95-daf1-0000-bb60-6e7e602005ac", "elements": [], "$geoip_city_name": "Jakarta", "$geoip_country_name": "Indonesia", "$geoip_country_code": "ID", "$geoip_continent_name": "Asia", "$geoip_continent_code": "AS", "$geoip_latitude": -6.2114, "$geoip_longitude": 106.8446, "$geoip_time_zone": "Asia/Jakarta", "$geoip_subdivision_1_code": "JK", "$geoip_subdivision_1_name": "Jakarta"}]