[{"distinct_id": "183131dc2c3d5-0468e3f67b268d-745e4346-448e0-183131dc2c415d", "event": "Web Session", "timestamp": "2022-10-09T04:38:48.348Z", "uuid": "0183bb09-d9ca-0000-a726-93742991617f", "elements": [], "$geoip_city_name": "Lhokseumawe", "$geoip_country_name": "Indonesia", "$geoip_country_code": "ID", "$geoip_continent_name": "Asia", "$geoip_continent_code": "AS", "$geoip_latitude": 5.1806, "$geoip_longitude": 97.1547, "$geoip_time_zone": "Asia/Jakarta", "$geoip_subdivision_1_code": "AC", "$geoip_subdivision_1_name": "Aceh"}]