[{"distinct_id": "14947", "event": "Feed: Created", "timestamp": "2022-10-11T09:31:00.000Z", "uuid": "0183c662-1768-0000-179f-7b2cfd81ed03", "elements": [], "$geoip_city_name": "Singapore", "$geoip_country_name": "Singapore", "$geoip_country_code": "SG", "$geoip_continent_name": "Asia", "$geoip_continent_code": "AS", "$geoip_latitude": 1.3036, "$geoip_longitude": 103.8554, "$geoip_time_zone": "Asia/Singapore"}, {"distinct_id": "14947", "event": "Mobile app: pond - view tabs - feed", "timestamp": "2022-10-11T09:30:43.365Z", "uuid": "0183c662-2429-0001-a26a-e871aaacbbaf", "elements": [], "$geoip_city_name": "Medan", "$geoip_country_name": "Indonesia", "$geoip_country_code": "ID", "$geoip_continent_name": "Asia", "$geoip_continent_code": "AS", "$geoip_latitude": 3.5847, "$geoip_longitude": 98.6629, "$geoip_time_zone": "Asia/Jakarta", "$geoip_subdivision_1_code": "SU", "$geoip_subdivision_1_name": "North Sumatra"}]