[{"distinct_id": "183e4f3c66c1b1-077e1604ecc86a-7325016c-42cc0-183e4f3c66dd2", "event": "$pageview", "timestamp": "2022-10-17T09:08:09.793Z", "uuid": "0183e533-53cb-0000-fd95-aead83c7311a", "elements": [], "$geoip_city_name": "Medan", "$geoip_country_name": "Indonesia", "$geoip_country_code": "ID", "$geoip_continent_name": "Asia", "$geoip_continent_code": "AS", "$geoip_latitude": 3.5847, "$geoip_longitude": 98.6629, "$geoip_time_zone": "Asia/Jakarta", "$geoip_subdivision_1_code": "SU", "$geoip_subdivision_1_name": "North Sumatra"}, {"distinct_id": "183e4f3c66c1b1-077e1604ecc86a-7325016c-42cc0-183e4f3c66dd2", "event": "$pageview", "timestamp": "2022-10-17T09:07:51.966Z", "uuid": "0183e533-0e22-0000-bb7f-9c3edaa0b54a", "elements": [], "$geoip_city_name": "Medan", "$geoip_country_name": "Indonesia", "$geoip_country_code": "ID", "$geoip_continent_name": "Asia", "$geoip_continent_code": "AS", "$geoip_latitude": 3.5847, "$geoip_longitude": 98.6629, "$geoip_time_zone": "Asia/Jakarta", "$geoip_subdivision_1_code": "SU", "$geoip_subdivision_1_name": "North Sumatra"}, {"distinct_id": "8212", "event": "Mobile app: fasting - add", "timestamp": "2022-10-17T09:07:14.062Z", "uuid": "0183e532-eca8-0000-ff3c-f3878af3c654", "elements": [], "$geoip_city_name": "Pekanbaru", "$geoip_country_name": "Indonesia", "$geoip_country_code": "ID", "$geoip_continent_name": "Asia", "$geoip_continent_code": "AS", "$geoip_latitude": 0.5167, "$geoip_longitude": 101.4417, "$geoip_time_zone": "Asia/Jakarta", "$geoip_subdivision_1_code": "RI", "$geoip_subdivision_1_name": "Riau"}]