[{"distinct_id": "18475cad6ef10-07e111fde0b403-9663344-448e0-18475cad6f054", "event": "Web Session", "timestamp": "2022-11-14T10:59:37.793Z", "uuid": "018475cb-73ab-0000-fdfc-9da2995cf81e", "elements": [], "$geoip_city_name": "Semarang", "$geoip_country_name": "Indonesia", "$geoip_country_code": "ID", "$geoip_continent_name": "Asia", "$geoip_continent_code": "AS", "$geoip_latitude": -6.9932, "$geoip_longitude": 110.4215, "$geoip_time_zone": "Asia/Jakarta", "$geoip_subdivision_1_code": "JT", "$geoip_subdivision_1_name": "Central Java"}]