[{"distinct_id": "15741", "event": "input-modal-feed filling form", "timestamp": "2022-11-14T11:12:56.155Z", "uuid": "018475d7-a7d4-0000-2d28-550b6893f010", "elements": [], "$geoip_city_name": "Cirebon", "$geoip_country_name": "Indonesia", "$geoip_country_code": "ID", "$geoip_continent_name": "Asia", "$geoip_continent_code": "AS", "$geoip_latitude": -6.7054, "$geoip_longitude": 108.5496, "$geoip_time_zone": "Asia/Jakarta", "$geoip_subdivision_1_code": "JB", "$geoip_subdivision_1_name": "West Java"}]