[{"distinct_id": "18476279d4f11f-0853061d954084-2a394d16-42cc0-18476279d511d6", "event": "Web Session", "timestamp": "2022-11-14T12:43:15.477Z", "uuid": "0184762a-50c4-0000-834d-081489eff10b", "elements": [], "$geoip_city_name": "Banjarmasin", "$geoip_country_name": "Indonesia", "$geoip_country_code": "ID", "$geoip_continent_name": "Asia", "$geoip_continent_code": "AS", "$geoip_latitude": -3.3219, "$geoip_longitude": 114.5871, "$geoip_time_zone": "Asia/Makassar", "$geoip_subdivision_1_code": "KS", "$geoip_subdivision_1_name": "South Kalimantan"}]