[{"distinct_id": "21928", "event": "input-modal-measurement filling form", "timestamp": "2022-11-21T23:54:15.654Z", "uuid": "01849c9d-2ee5-0000-cf8c-2b3a9db36e23", "elements": [], "$geoip_city_name": "Mataram", "$geoip_country_name": "Indonesia", "$geoip_country_code": "ID", "$geoip_continent_name": "Asia", "$geoip_continent_code": "AS", "$geoip_latitude": -8.5842, "$geoip_longitude": 116.1187, "$geoip_time_zone": "Asia/Makassar", "$geoip_subdivision_1_code": "NB", "$geoip_subdivision_1_name": "West Nusa Tenggara"}, {"distinct_id": "21928", "event": "input-modal-measurement filling form", "timestamp": "2022-11-21T23:54:18.534Z", "uuid": "01849c9d-3aa6-0000-1a64-fedd1e3be3f5", "elements": [], "$geoip_city_name": "Mataram", "$geoip_country_name": "Indonesia", "$geoip_country_code": "ID", "$geoip_continent_name": "Asia", "$geoip_continent_code": "AS", "$geoip_latitude": -8.5842, "$geoip_longitude": 116.1187, "$geoip_time_zone": "Asia/Makassar", "$geoip_subdivision_1_code": "NB", "$geoip_subdivision_1_name": "West Nusa Tenggara"}]