[{"distinct_id": "184bd24dc1fe9-09a09c51322d8a-5c531d38-42cc0-184bd24dc20fd", "event": "Visit Detail Newsfeed", "timestamp": "2022-11-29T07:37:39.408Z", "uuid": "0184c251-fb55-0000-52f7-149ed00c6546", "elements": [], "$geoip_city_name": "Mataram", "$geoip_country_name": "Indonesia", "$geoip_country_code": "ID", "$geoip_continent_name": "Asia", "$geoip_continent_code": "AS", "$geoip_latitude": -8.5842, "$geoip_longitude": 116.1187, "$geoip_time_zone": "Asia/Makassar", "$geoip_subdivision_1_code": "NB", "$geoip_subdivision_1_name": "West Nusa Tenggara"}]