[{"distinct_id": "14987", "event": "$identify", "timestamp": "2022-10-19T06:09:37.416Z", "uuid": "0183eedc-968f-0000-6a5b-3f67f9cfb072", "elements": [], "$geoip_city_name": "Jakarta", "$geoip_country_name": "Indonesia", "$geoip_country_code": "ID", "$geoip_continent_name": "Asia", "$geoip_continent_code": "AS", "$geoip_latitude": -6.2114, "$geoip_longitude": 106.8446, "$geoip_time_zone": "Asia/Jakarta", "$geoip_subdivision_1_code": "JK", "$geoip_subdivision_1_name": "Jakarta"}, {"distinct_id": "21367", "event": "input spreadsheet - save changes", "timestamp": "2022-10-19T06:10:20.470Z", "uuid": "0183eedd-44e3-0000-b615-bf164f07bde6", "elements": [], "$geoip_city_name": "Quelimane", "$geoip_country_name": "Mozambique", "$geoip_country_code": "MZ", "$geoip_continent_name": "Africa", "$geoip_continent_code": "AF", "$geoip_latitude": -17.8765, "$geoip_longitude": 36.8861, "$geoip_time_zone": "Africa/Maputo", "$geoip_subdivision_1_code": "Q", "$geoip_subdivision_1_name": "Provincia de Zambezia"}]