[{"distinct_id": "183e1348a3f1e5-06e9e96a4de53c-2b50356c-53c31-183e1348a40115", "event": "$pageleave", "timestamp": "2022-10-16T14:36:41.715Z", "uuid": "0183e139-bf7b-0001-3c4b-20a1c0baf670", "elements": [], "$geoip_city_name": "Surabaya", "$geoip_country_name": "Indonesia", "$geoip_country_code": "ID", "$geoip_continent_name": "Asia", "$geoip_continent_code": "AS", "$geoip_latitude": -7.2484, "$geoip_longitude": 112.7419, "$geoip_time_zone": "Asia/Jakarta", "$geoip_subdivision_1_code": "JI", "$geoip_subdivision_1_name": "East Java"}]