[{"distinct_id": "6325", "event": "Change Measurement Graph Dropdown", "timestamp": "2022-10-05T00:28:46.198Z", "uuid": "0183a58b-8036-0000-cf1e-8263214cc9e4", "elements": [], "$geoip_city_name": "Semarang", "$geoip_country_name": "Indonesia", "$geoip_country_code": "ID", "$geoip_continent_name": "Asia", "$geoip_continent_code": "AS", "$geoip_latitude": -6.9932, "$geoip_longitude": 110.4215, "$geoip_time_zone": "Asia/Jakarta", "$geoip_subdivision_1_code": "JT", "$geoip_subdivision_1_name": "Central Java"}]