[{"distinct_id": "18475d620e95c-031c25540f5955-7e064242-5f070-18475d620ea4", "event": "$pageview", "timestamp": "2022-11-18T03:03:22.928Z", "uuid": "018488b0-dc38-0000-e4ef-1cf7ae4e9fe8", "elements": [], "$geoip_city_name": "Bandar Lampung", "$geoip_country_name": "Indonesia", "$geoip_country_code": "ID", "$geoip_continent_name": "Asia", "$geoip_continent_code": "AS", "$geoip_latitude": -5.4291, "$geoip_longitude": 105.2615, "$geoip_time_zone": "Asia/Jakarta", "$geoip_subdivision_1_code": "LA", "$geoip_subdivision_1_name": "Lampung"}]