[{"distinct_id": "15689", "event": "$pageleave", "timestamp": "2022-10-18T02:44:33.490Z", "uuid": "0183e8fa-7c5e-0001-92ce-97ea96842d0e", "elements": [], "$geoip_city_name": "Ho Chi Minh City", "$geoip_country_name": "Vietnam", "$geoip_country_code": "VN", "$geoip_continent_name": "Asia", "$geoip_continent_code": "AS", "$geoip_latitude": 10.8326, "$geoip_longitude": 106.6581, "$geoip_time_zone": "Asia/Ho_Chi_Minh", "$geoip_subdivision_1_code": "SG", "$geoip_subdivision_1_name": "Ho Chi Minh"}, {"distinct_id": "15689", "event": "Opened input excel", "timestamp": "2022-10-18T02:44:37.636Z", "uuid": "0183e8fa-91cc-0000-dd5c-39271607001f", "elements": [], "$geoip_city_name": "Ho Chi Minh City", "$geoip_country_name": "Vietnam", "$geoip_country_code": "VN", "$geoip_continent_name": "Asia", "$geoip_continent_code": "AS", "$geoip_latitude": 10.8326, "$geoip_longitude": 106.6581, "$geoip_time_zone": "Asia/Ho_Chi_Minh", "$geoip_subdivision_1_code": "SG", "$geoip_subdivision_1_name": "Ho Chi Minh"}, {"distinct_id": "15689", "event": "$pageview", "timestamp": "2022-10-18T02:44:34.610Z", "uuid": "0183e8fa-80b8-0000-6b10-e8fd2e9e5530", "elements": [], "$geoip_city_name": "Ho Chi Minh City", "$geoip_country_name": "Vietnam", "$geoip_country_code": "VN", "$geoip_continent_name": "Asia", "$geoip_continent_code": "AS", "$geoip_latitude": 10.8326, "$geoip_longitude": 106.6581, "$geoip_time_zone": "Asia/Ho_Chi_Minh", "$geoip_subdivision_1_code": "SG", "$geoip_subdivision_1_name": "Ho Chi Minh"}]