[{"distinct_id": "183c09ef9a00-0bd0ce5f23817c-50521a36-5768c-183c09ef9a172", "event": "$pageview", "timestamp": "2022-10-10T06:40:05.187Z", "uuid": "0183c09f-3e4b-0000-ba95-f01416eae2e9", "elements": [], "$geoip_city_name": "Surabaya", "$geoip_country_name": "Indonesia", "$geoip_country_code": "ID", "$geoip_continent_name": "Asia", "$geoip_continent_code": "AS", "$geoip_latitude": -7.2484, "$geoip_longitude": 112.7419, "$geoip_time_zone": "Asia/Jakarta", "$geoip_subdivision_1_code": "JI", "$geoip_subdivision_1_name": "East Java"}]